sortition_algorithms/__init__.py
sortition_algorithms/__main__.py
sortition_algorithms/adapters.py
sortition_algorithms/core.py
sortition_algorithms/error_messages.py
sortition_algorithms/errors.py
sortition_algorithms/features.py
sortition_algorithms/people.py
sortition_algorithms/people_features.py
sortition_algorithms/py.typed
sortition_algorithms/report_messages.py
sortition_algorithms/settings.py
sortition_algorithms/utils.py
sortition_algorithms/committee_generation/__init__.py
sortition_algorithms/committee_generation/common.py
sortition_algorithms/committee_generation/diversimax.py
sortition_algorithms/committee_generation/legacy.py
sortition_algorithms/committee_generation/leximin.py
sortition_algorithms/committee_generation/maximin.py
sortition_algorithms/committee_generation/nash.py
sortition_algorithms-0.11.4.dist-info/METADATA
sortition_algorithms-0.11.4.dist-info/WHEEL
sortition_algorithms-0.11.4.dist-info/entry_points.txt
sortition_algorithms-0.11.4.dist-info/licenses/LICENSE
sortition_algorithms-0.11.4.dist-info/RECORD
