Metadata-Version: 2.4
Name: sortition-algorithms
Version: 0.11.4
Summary: A package containing algorithms for sortition - democratic lotteries.
Project-URL: Homepage, https://sortitionfoundation.github.io/sortition-algorithms/
Project-URL: Repository, https://github.com/sortitionfoundation/sortition-algorithms
Project-URL: Documentation, https://sortitionfoundation.github.io/sortition-algorithms/
Author-email: "Hamish Downer (Sortition Foundation)" <hamish@sortitionfoundation.org>, "Brett Hennig (Sortition Foundation)" <brett@sortitionfoundation.org>, "Nick Gill (Sortition Foundation)" <nick@sortitionfoundation.org>, Paul Gölz <pgoelz@cs.cmu.edu>
License-File: LICENSE
Keywords: python
Classifier: Intended Audience :: Developers
Classifier: Programming Language :: Python
Classifier: Programming Language :: Python :: 3
Classifier: Programming Language :: Python :: 3.11
Classifier: Programming Language :: Python :: 3.12
Classifier: Topic :: Software Development :: Libraries :: Python Modules
Requires-Python: <3.13,>=3.11
Requires-Dist: attrs>=25.4.0
Requires-Dist: cattrs>=25.1.0
Requires-Dist: cvxpy>=1.6.5
Requires-Dist: gspread>=6.2.1
Requires-Dist: mip==1.15.0
Requires-Dist: numpy>=2.3.4
Requires-Dist: oauth2client>=4.1.3
Requires-Dist: pandas==2.3.3
Requires-Dist: requests>=2.32.0
Requires-Dist: scikit-learn==1.7.2
Requires-Dist: tabulate>=0.9.0
Provides-Extra: cli
Requires-Dist: click>=8.2.1; extra == 'cli'
Provides-Extra: gurobi
Requires-Dist: gurobipy>=12.0.2; extra == 'gurobi'
